nkia/ml/classify_products.py
nkia/ml/cnn_nlp_model.py
utils/utils.py
nkia-1.9.1.dist-info/LICENSE
nkia-1.9.1.dist-info/METADATA
nkia-1.9.1.dist-info/WHEEL
nkia-1.9.1.dist-info/top_level.txt
nkia-1.9.1.dist-info/RECORD
