Metadata-Version: 2.1
Name: nkia
Version: 1.9.1
Summary: This is a module to predict the products category using artificial inteligence.
Home-page: https://bitbucket.org/nksistemasdeinformacao/servicos-biodigital/src/master/
Author: NK Sistemas de Informacao em Saude
Author-email: ti@nkodontologia.com.br
License: Apache License 2.0
Download-URL: https://bitbucket.org/nksistemasdeinformacao/servicos-biodigital/src/master/
Keywords: tensorflow,nlp,nk,python3,cnn,food-products
Platform: UNKNOWN
Classifier: Operating System :: OS Independent
Classifier: Programming Language :: Python :: 3
Classifier: Development Status :: 3 - Alpha
Classifier: License :: OSI Approved :: Apache Software License
Classifier: Programming Language :: Python
Classifier: Topic :: Communications :: Email
Requires-Python: >=3.6
Requires-Dist: tensorflow (==2.2.0)
Requires-Dist: numpy (==1.19.1)
Requires-Dist: tensorflow-datasets (==3.2.1)
Requires-Dist: Unidecode (==1.1.1)
Requires-Dist: nltk (==3.5)
Requires-Dist: gdown (==3.12.0)
Requires-Dist: scikit-learn (==0.23.2)
Requires-Dist: symspellpy (==6.5.2)
Provides-Extra: dev
Requires-Dist: pytest (>=3.7) ; extra == 'dev'
